multivae/__init__.py
multivae/data/__init__.py
multivae/data/utils.py
multivae/data/datasets/__init__.py
multivae/data/datasets/base.py
multivae/data/datasets/celeba.py
multivae/data/datasets/celebattr.py
multivae/data/datasets/cub.py
multivae/data/datasets/mhd.py
multivae/data/datasets/mmnist.py
multivae/data/datasets/mnist_labels.py
multivae/data/datasets/mnist_svhn.py
multivae/data/datasets/translated_mmnist.py
multivae/data/datasets/utils.py
multivae/metrics/__init__.py
multivae/metrics/base/__init__.py
multivae/metrics/base/evaluator_class.py
multivae/metrics/base/evaluator_config.py
multivae/metrics/classifiers/__init__.py
multivae/metrics/classifiers/mmnist.py
multivae/metrics/coherences/__init__.py
multivae/metrics/coherences/coherences.py
multivae/metrics/coherences/coherences_config.py
multivae/metrics/fids/__init__.py
multivae/metrics/fids/fids.py
multivae/metrics/fids/fids_config.py
multivae/metrics/fids/inception_networks.py
multivae/metrics/latent_clustering/__init__.py
multivae/metrics/latent_clustering/clustering_class.py
multivae/metrics/latent_clustering/clustering_config.py
multivae/metrics/likelihoods/__init__.py
multivae/metrics/likelihoods/likelihoods.py
multivae/metrics/likelihoods/likelihoods_config.py
multivae/metrics/reconstruction/__init__.py
multivae/metrics/reconstruction/reconstruction.py
multivae/metrics/reconstruction/reconstruction_config.py
multivae/metrics/visualization/__init__.py
multivae/metrics/visualization/visualization_class.py
multivae/metrics/visualization/visualize_config.py
multivae/models/__init__.py
multivae/models/auto_model/__init__.py
multivae/models/auto_model/auto_config.py
multivae/models/auto_model/auto_model.py
multivae/models/base/__init__.py
multivae/models/base/base_ae_model.py
multivae/models/base/base_config.py
multivae/models/base/base_model.py
multivae/models/base/base_utils.py
multivae/models/cmvae/__init__.py
multivae/models/cmvae/cmvae_config.py
multivae/models/cmvae/cmvae_model.py
multivae-1.0.3.dist-info/licenses/LICENSE
multivae-1.0.3.dist-info/METADATA
multivae-1.0.3.dist-info/WHEEL
multivae-1.0.3.dist-info/top_level.txt
multivae-1.0.3.dist-info/RECORD
