Metadata-Version: 2.4
Name: multivae
Version: 1.0.3
Summary: Unifying Generative Multimodel Variational Autoencoders in Pytorch
Home-page: https://github.com/AgatheSenellart/MultiVae
Author: Agathe Senellart, Clement Chadebec
Author-email: agathe.senellart@inria.fr
Project-URL: Bug Tracker, https://github.com/AgatheSenellart/MultiVae/issues
Classifier: Programming Language :: Python :: 3
Classifier: Programming Language :: Python :: 3.8
Classifier: Programming Language :: Python :: 3.9
Classifier: Programming Language :: Python :: 3.10
Classifier: License :: OSI Approved :: Apache Software License
Classifier: Operating System :: OS Independent
Requires-Python: >=3.8
License-File: LICENSE
Requires-Dist: pythae
Requires-Dist: cloudpickle>=2.1.0
Requires-Dist: numpy>=1.19
Requires-Dist: pydantic>=2.0
Requires-Dist: scikit-learn
Requires-Dist: scipy>=1.7.1
Requires-Dist: torch>=1.10.1
Requires-Dist: tqdm
Requires-Dist: typing_extensions
Requires-Dist: dataclasses>=0.6
Requires-Dist: torchvision
Requires-Dist: pandas
Requires-Dist: nltk
Requires-Dist: torchmetrics
Requires-Dist: matplotlib
Dynamic: author
Dynamic: author-email
Dynamic: classifier
Dynamic: description
Dynamic: description-content-type
Dynamic: home-page
Dynamic: license-file
Dynamic: project-url
Dynamic: requires-dist
Dynamic: requires-python
Dynamic: summary
